GmailBox/__init__.py
GmailBox/async_session.py
GmailBox/asyncio.py
GmailBox/my_types.py
GmailBox/session.py
GmailBox-1.0.0.dist-info/METADATA
GmailBox-1.0.0.dist-info/WHEEL
GmailBox-1.0.0.dist-info/top_level.txt
GmailBox-1.0.0.dist-info/RECORD
