Metadata-Version: 2.1
Name: GmailBox
Version: 1.0.0
Summary: With this library, you can create random Gmail and receive messages
Author: Hamo
License: LGPLv3
Keywords: gmail,mail,GmailBox,inbox,email,Tempmail,Tempgmail
Classifier: Development Status :: 3 - Alpha
Classifier: Intended Audience :: Developers
Classifier: License :: OSI Approved :: GNU Lesser General Public License v3 (LGPLv3)
Classifier: Programming Language :: Python :: 3
Classifier: Operating System :: OS Independent
Requires-Dist: requests
Requires-Dist: beautifulsoup4
Requires-Dist: aiohttp
Requires-Dist: asyncio
Requires-Dist: pypasser
